{
    "titulo": "Kaiju No. 8: Misión de reconocimiento",
    "url": "https://www.cinesa.es/peliculas/kaiju-no-8-mision-de-reconocimiento/HO00002171/",
    "imagen_local": "/home/dev/gadget/data/imagenes/imagen_sin_titulo.jpg",
    "duracion": "2h 0m",
    "fecha_estreno": "9 mayo 2025",
    "generos": [
        "Acción",
        "Animación"
    ],
    "clasificacion": "No recomendada para menores de 12 años",
    "directores": "Shigeyuki Miya, Tomomi Kamiya",
    "actores": [
        "Wataru Kato",
        "Masaya Fukunishi"
    ],
    "sinopsis": "En un Japón repleto de Kaiju, Kafka Hibino trabaja como limpiador de monstruos. Tras reencontrarse con su amiga de la infancia, Mina Ashiro, una joven promesa de las Fuerzas de Defensa que luchan contra los Kaiju, decide intentar cumplir su antiguo sueño de unirse a las Fuerzas... cuando de repente se transforma en el poderoso Kaiju nº 8. Con la ayuda de un colega más joven, Reno Ichikawa, Kafka oculta su identidad mientras lucha por cumplir el sueño de su vida: aprobar el examen de las Fuerzas de Defensa y así poder estar al lado de Mina. Pero cuando un misterioso Kaiju inteligente ataca una base de las Fuerzas de Defensa, Kafka se enfrenta a una decisión crucial en una situación desesperada...",
    "poster_local": "/home/dev/gadget/data/imagenes/Kaiju_No_8_Misión_de_reconocimiento.jpg",
    "sesiones": [],
    "fecha_scraping": "2025-05-20T04:44:21.555188"
}